Metadata-Version: 2.1
Name: bip_utils
Version: 2.9.2
Summary: Generation of mnemonics, seeds, private/public keys and addresses for different types of cryptocurrencies
Home-page: https://github.com/ebellocchia/bip_utils
Download-URL: https://github.com/ebellocchia/bip_utils/archive/v2.9.2.tar.gz
Author: Emanuele Bellocchia
Author-email: ebellocchia@gmail.com
Maintainer: Emanuele Bellocchia
Maintainer-email: ebellocchia@gmail.com
License: MIT
Keywords: python,cryptography,ecdsa,ed25519,ed25519-blake2b,nist256p1,secp256k1,sr25519,wallet,hd-wallet,slip10,slip32,bip38,bip39,bip39-substrate,bip32,bip44,bip49,bip84,bip86,bip173,bip350,brainwallet,base58,ss58,bech32,bech32m,segwit,electrum,substrate,taproot,daedalus,byron,shelley,akash,algorand,aptos,arbitrum,atom,avalanche,avax,axelar,band protocol,binance chain,binance smart chain,bitcoin,bitcoin cash,bitcoinsv,bnb,cardano,cardano-byron,cardano-shelley,celo,certik,cosmos,dash,dogecoin,ec
Platform: any
Classifier: Programming Language :: Python :: 3.7
Classifier: Programming Language :: Python :: 3.8
Classifier: Programming Language :: Python :: 3.9
Classifier: Programming Language :: Python :: 3.10
Classifier: Programming Language :: Python :: 3.11
Classifier: Programming Language :: Python :: 3.12
Classifier: Development Status :: 5 - Production/Stable
Classifier: License :: OSI Approved :: MIT License
Classifier: Operating System :: OS Independent
Classifier: Intended Audience :: Developers
Requires-Python: >=3.7
License-File: LICENSE
Requires-Dist: cbor2 <6.0.0,>=5.1.2
Requires-Dist: crcmod ~=1.7
Requires-Dist: ecdsa ~=0.17
Requires-Dist: pycryptodome ~=3.15
Requires-Dist: pynacl ~=1.5
Requires-Dist: py-sr25519-bindings <2.0.0,>=0.1.3 ; python_version < "3.10"
Requires-Dist: ed25519-blake2b <2.0.0,>=1.4 ; python_version < "3.12"
Requires-Dist: coincurve >=16.0.0 ; python_version == "3.10"
Requires-Dist: py-sr25519-bindings <2.0.0,>=0.1.4 ; python_version == "3.10"
Requires-Dist: coincurve >=18.0.0 ; python_version == "3.11"
Requires-Dist: coincurve <19.0.0,>=15.0.1 ; python_version == "3.7"
Requires-Dist: typing-extensions >=3.7.2 ; python_version == "3.7"
Requires-Dist: coincurve >=15.0.1 ; python_version > "3.7" and python_version < "3.10"
Requires-Dist: py-sr25519-bindings <2.0.0,>=0.2.0 ; python_version >= "3.11"
Requires-Dist: coincurve >=19.0.1 ; python_version >= "3.12"
Requires-Dist: ed25519-blake2b <2.0.0,>=1.4.1 ; python_version >= "3.12"
Provides-Extra: develop
Requires-Dist: coverage >=5.3 ; extra == 'develop'
Requires-Dist: flake8 >=3.8 ; extra == 'develop'
Requires-Dist: isort >=5.8 ; extra == 'develop'
Requires-Dist: mypy >=0.900 ; extra == 'develop'
Requires-Dist: prospector[with_mypy,with_pyroma] >=1.7 ; extra == 'develop'
Requires-Dist: pytest >=7.0 ; extra == 'develop'
Requires-Dist: pytest-cov >=2.10 ; extra == 'develop'
